stocks_historical/__init__.py
stocks_historical/constants.py
stocks_historical/fetcher.py
stocks_historical/nasdaq.py
stocks_historical/nyse.py
stocks_historical/utils.py
tests/__init__.py
tests/test_fetcher.py
tests/test_nasdaq.py
tests/test_nyse.py
stocks_historical-1.0.1.dist-info/LICENSE.txt
stocks_historical-1.0.1.dist-info/METADATA
stocks_historical-1.0.1.dist-info/WHEEL
stocks_historical-1.0.1.dist-info/top_level.txt
stocks_historical-1.0.1.dist-info/RECORD
