Metadata-Version: 2.1
Name: stocks_historical
Version: 1.0.1
Summary: A Python package to access historical stock data for NASDAQ and NYSE.
Home-page: https://github.com/mantey-github/stocks-historical
Download-URL: https://github.com/mantey-github/stocks-historical/releases
Author: Daniel Mantey
Author-email: contactmantey@gmail.com
Classifier: Programming Language :: Python :: 3
Classifier: License :: OSI Approved :: MIT License
Classifier: Operating System :: OS Independent
Requires-Python: >=3.7
License-File: LICENSE.txt
Requires-Dist: requests
Requires-Dist: pandas
Requires-Dist: setuptools
